shipyard_motherduck/__init__.py
shipyard_motherduck/cli/authtest.py
shipyard_motherduck/cli/execute.py
shipyard_motherduck/cli/fetch.py
shipyard_motherduck/cli/upload.py
shipyard_motherduck/exceptions.py
shipyard_motherduck/motherduck.py
shipyard_motherduck-0.1.2.dist-info/METADATA
shipyard_motherduck-0.1.2.dist-info/WHEEL
shipyard_motherduck-0.1.2.dist-info/RECORD
