Metadata-Version: 2.1
Name: shipyard-motherduck
Version: 0.1.2
Summary: A local client for working with Python and MotherDuck
Author: wrp801
Author-email: wespoulsen@gmail.com
Requires-Python: >=3.9,<4.0
Classifier: Programming Language :: Python :: 3
Classifier: Programming Language :: Python :: 3.9
Classifier: Programming Language :: Python :: 3.10
Classifier: Programming Language :: Python :: 3.11
Requires-Dist: duckdb (==0.9.2)
Requires-Dist: pandas (>=2.0,<3.0)
Requires-Dist: shipyard-bp-utils (>=1.2.1,<2.0.0)
Requires-Dist: shipyard-templates (>=0.8.2,<0.9.0)
Requires-Dist: sqlalchemy (>=2.0.29,<3.0.0)
